{"day": "2020-04-06", "latitude": 43.7881742, "longitude": 11.226609, "avgDailyTemp": 18.36, "avgDailyCo2": 424.75, "avgDailyRad": 31.19, "avgDailyO3": 77.9, "avgDailyNo2": 78.78, "avgDailyCo": 189.26, "avgDailyVoc": 765.95, "avgDailyPm2_5": 11.47, "avgDailyPm10": 3.35, "avgDailyDs18": 28.47, "data": [{"time": "2020-04-06_00", "missingData": "false", "avgTemp": 16.12, "avgCo2": 410.19, "avgRad": 33.3, "avg03": 97.35, "avgNo2": 66.13, "avgCo": 181.74, "avgVoc": 744.06, "avgPm2_5": 10.42, "avgPm10": 2.48, "avgDs18": 26.47, "samplxH": 31}, {"time": "2020-04-06_01", "missingData": "false", "avgTemp": 15.81, "avgCo2": 411.09, "avgRad": 32.85, "avg03": 98.24, "avgNo2": 64.03, "avgCo": 180.06, "avgVoc": 741.68, "avgPm2_5": 10.0, "avgPm10": 2.29, "avgDs18": 26.19, "samplxH": 34}, {"time": "2020-04-06_02", "missingData": "false", "avgTemp": 15.5, "avgCo2": 409.91, "avgRad": 34.29, "avg03": 100.91, "avgNo2": 62.94, "avgCo": 180.78, "avgVoc": 739.84, "avgPm2_5": 9.91, "avgPm10": 2.56, "avgDs18": 25.86, "samplxH": 32}, {"time": "2020-04-06_03", "missingData": "false", "avgTemp": 15.34, "avgCo2": 411.33, "avgRad": 36.25, "avg03": 99.88, "avgNo2": 63.97, "avgCo": 183.88, "avgVoc": 742.85, "avgPm2_5": 10.45, "avgPm10": 2.45, "avgDs18": 25.68, "samplxH": 33}, {"time": "2020-04-06_04", "missingData": "false", "avgTemp": 15.1, "avgCo2": 416.16, "avgRad": 37.76, "avg03": 90.65, "avgNo2": 68.35, "avgCo": 186.32, "avgVoc": 752.29, "avgPm2_5": 10.45, "avgPm10": 2.61, "avgDs18": 25.49, "samplxH": 31}, {"time": "2020-04-06_05", "missingData": "false", "avgTemp": 15.13, "avgCo2": 415.58, "avgRad": 38.92, "avg03": 86.47, "avgNo2": 73.03, "avgCo": 189.92, "avgVoc": 762.94, "avgPm2_5": 10.5, "avgPm10": 2.81, "avgDs18": 25.45, "samplxH": 36}, {"time": "2020-04-06_06", "missingData": "false", "avgTemp": 16.02, "avgCo2": 412.23, "avgRad": 39.33, "avg03": 78.31, "avgNo2": 75.49, "avgCo": 194.86, "avgVoc": 763.49, "avgPm2_5": 10.97, "avgPm10": 3.03, "avgDs18": 26.18, "samplxH": 35}, {"time": "2020-04-06_07", "missingData": "false", "avgTemp": 17.29, "avgCo2": 408.97, "avgRad": 36.66, "avg03": 82.14, "avgNo2": 74.78, "avgCo": 195.72, "avgVoc": 755.89, "avgPm2_5": 11.92, "avgPm10": 3.58, "avgDs18": 27.22, "samplxH": 36}, {"time": "2020-04-06_08", "missingData": "false", "avgTemp": 18.75, "avgCo2": 428.75, "avgRad": 32.95, "avg03": 79.54, "avgNo2": 79.38, "avgCo": 196.38, "avgVoc": 763.0, "avgPm2_5": 12.25, "avgPm10": 3.96, "avgDs18": 28.47, "samplxH": 24}, {"time": "2020-04-06_09", "missingData": "false", "avgTemp": 20.03, "avgCo2": 427.48, "avgRad": 28.67, "avg03": 75.16, "avgNo2": 81.44, "avgCo": 193.92, "avgVoc": 766.04, "avgPm2_5": 12.8, "avgPm10": 4.16, "avgDs18": 29.77, "samplxH": 25}, {"time": "2020-04-06_10", "missingData": "false", "avgTemp": 21.38, "avgCo2": 422.73, "avgRad": 25.32, "avg03": 69.73, "avgNo2": 86.1, "avgCo": 192.9, "avgVoc": 778.57, "avgPm2_5": 12.4, "avgPm10": 3.63, "avgDs18": 30.95, "samplxH": 30}, {"time": "2020-04-06_11", "missingData": "false", "avgTemp": 21.81, "avgCo2": 421.85, "avgRad": 24.69, "avg03": 67.56, "avgNo2": 86.88, "avgCo": 192.38, "avgVoc": 781.12, "avgPm2_5": 11.62, "avgPm10": 3.32, "avgDs18": 31.42, "samplxH": 34}, {"time": "2020-04-06_12", "missingData": "false", "avgTemp": 22.33, "avgCo2": 422.0, "avgRad": 24.32, "avg03": 65.58, "avgNo2": 88.96, "avgCo": 193.0, "avgVoc": 784.96, "avgPm2_5": 11.62, "avgPm10": 3.54, "avgDs18": 31.79, "samplxH": 26}, {"time": "2020-04-06_13", "missingData": "false", "avgTemp": 22.66, "avgCo2": 419.92, "avgRad": 23.8, "avg03": 64.88, "avgNo2": 89.25, "avgCo": 193.08, "avgVoc": 785.38, "avgPm2_5": 11.58, "avgPm10": 3.46, "avgDs18": 32.08, "samplxH": 24}, {"time": "2020-04-06_14", "missingData": "false", "avgTemp": 23.14, "avgCo2": 421.19, "avgRad": 23.63, "avg03": 62.48, "avgNo2": 93.15, "avgCo": 195.56, "avgVoc": 792.63, "avgPm2_5": 11.52, "avgPm10": 3.63, "avgDs18": 33.13, "samplxH": 27}, {"time": "2020-04-06_15", "missingData": "false", "avgTemp": 21.93, "avgCo2": 424.0, "avgRad": 25.93, "avg03": 64.83, "avgNo2": 87.03, "avgCo": 193.93, "avgVoc": 780.31, "avgPm2_5": 12.17, "avgPm10": 3.66, "avgDs18": 31.93, "samplxH": 29}, {"time": "2020-04-06_16", "missingData": "false", "avgTemp": 21.06, "avgCo2": 426.04, "avgRad": 27.87, "avg03": 71.41, "avgNo2": 80.85, "avgCo": 194.7, "avgVoc": 767.89, "avgPm2_5": 12.3, "avgPm10": 3.93, "avgDs18": 30.98, "samplxH": 27}, {"time": "2020-04-06_17", "missingData": "false", "avgTemp": 20.24, "avgCo2": 430.15, "avgRad": 26.31, "avg03": 76.27, "avgNo2": 75.7, "avgCo": 188.79, "avgVoc": 760.94, "avgPm2_5": 11.7, "avgPm10": 3.52, "avgDs18": 30.25, "samplxH": 33}, {"time": "2020-04-06_18", "missingData": "false", "avgTemp": 19.17, "avgCo2": 434.59, "avgRad": 26.44, "avg03": 82.09, "avgNo2": 70.24, "avgCo": 184.62, "avgVoc": 755.15, "avgPm2_5": 11.32, "avgPm10": 3.59, "avgDs18": 29.35, "samplxH": 34}, {"time": "2020-04-06_19", "missingData": "false", "avgTemp": 18.57, "avgCo2": 436.96, "avgRad": 27.75, "avg03": 81.7, "avgNo2": 71.26, "avgCo": 184.0, "avgVoc": 758.35, "avgPm2_5": 11.7, "avgPm10": 3.52, "avgDs18": 29.0, "samplxH": 23}, {"time": "2020-04-06_20", "missingData": "false", "avgTemp": 18.18, "avgCo2": 439.5, "avgRad": 29.25, "avg03": 68.38, "avgNo2": 99.83, "avgCo": 178.46, "avgVoc": 773.92, "avgPm2_5": 11.75, "avgPm10": 3.71, "avgDs18": 28.22, "samplxH": 24}, {"time": "2020-04-06_21", "missingData": "false", "avgTemp": 17.72, "avgCo2": 441.79, "avgRad": 31.36, "avg03": 70.95, "avgNo2": 87.74, "avgCo": 185.71, "avgVoc": 776.82, "avgPm2_5": 12.66, "avgPm10": 4.05, "avgDs18": 28.21, "samplxH": 38}, {"time": "2020-04-06_22", "missingData": "false", "avgTemp": 16.57, "avgCo2": 453.44, "avgRad": 35.53, "avg03": 60.62, "avgNo2": 92.68, "avgCo": 192.38, "avgVoc": 791.38, "avgPm2_5": 12.47, "avgPm10": 3.94, "avgDs18": 27.08, "samplxH": 34}, {"time": "2020-04-06_23", "missingData": "false", "avgTemp": 15.89, "avgCo2": 449.29, "avgRad": 35.46, "avg03": 64.97, "avgNo2": 82.84, "avgCo": 191.08, "avgVoc": 775.08, "avgPm2_5": 11.63, "avgPm10": 3.47, "avgDs18": 26.61, "samplxH": 38}]}