{"day": "2020-04-11", "latitude": 43.7526116, "longitude": 11.231073, "avgDailyTemp": 14.83, "avgDailyCo2": 418.55, "avgDailyRad": 50.22, "avgDailyO3": 9999.0, "avgDailyNo2": 14.89, "avgDailyCo": 219.57, "avgDailyVoc": 290.41, "avgDailyPm2_5": 0.0, "avgDailyPm10": 0.0, "avgDailyDs18": 19.32, "data": [{"time": "2020-04-11_00", "missingData": "false", "avgTemp": 7.86, "avgCo2": 436.88, "avgRad": 58.96, "avg03": 9999.0, "avgNo2": 18.82, "avgCo": 200.95, "avgVoc": 303.88, "avgPm2_5": 0.0, "avgPm10": 0.0, "avgDs18": 12.61, "samplxH": 40}, {"time": "2020-04-11_01", "missingData": "false", "avgTemp": 6.93, "avgCo2": 437.64, "avgRad": 61.53, "avg03": 9999.0, "avgNo2": 14.18, "avgCo": 199.51, "avgVoc": 295.0, "avgPm2_5": 0.0, "avgPm10": 0.0, "avgDs18": 11.71, "samplxH": 39}, {"time": "2020-04-11_02", "missingData": "false", "avgTemp": 6.3, "avgCo2": 439.7, "avgRad": 65.21, "avg03": 9999.0, "avgNo2": 16.45, "avgCo": 201.78, "avgVoc": 302.35, "avgPm2_5": 0.0, "avgPm10": 0.0, "avgDs18": 10.91, "samplxH": 40}, {"time": "2020-04-11_03", "missingData": "false", "avgTemp": 5.12, "avgCo2": 446.38, "avgRad": 69.83, "avg03": 9999.0, "avgNo2": 17.69, "avgCo": 201.87, "avgVoc": 305.9, "avgPm2_5": 0.0, "avgPm10": 0.0, "avgDs18": 9.86, "samplxH": 39}, {"time": "2020-04-11_04", "missingData": "false", "avgTemp": 4.88, "avgCo2": 441.15, "avgRad": 70.41, "avg03": 9999.0, "avgNo2": 15.43, "avgCo": 201.68, "avgVoc": 302.32, "avgPm2_5": 0.0, "avgPm10": 0.0, "avgDs18": 9.44, "samplxH": 40}, {"time": "2020-04-11_05", "missingData": "false", "avgTemp": 4.95, "avgCo2": 442.33, "avgRad": 72.57, "avg03": 9999.0, "avgNo2": 17.15, "avgCo": 205.72, "avgVoc": 307.38, "avgPm2_5": 0.0, "avgPm10": 0.0, "avgDs18": 9.58, "samplxH": 39}, {"time": "2020-04-11_06", "missingData": "false", "avgTemp": 10.84, "avgCo2": 430.1, "avgRad": 59.43, "avg03": 9999.0, "avgNo2": 18.52, "avgCo": 216.07, "avgVoc": 310.12, "avgPm2_5": 0.0, "avgPm10": 0.0, "avgDs18": 13.74, "samplxH": 40}, {"time": "2020-04-11_07", "missingData": "false", "avgTemp": 15.57, "avgCo2": 413.05, "avgRad": 48.48, "avg03": 9999.0, "avgNo2": 16.26, "avgCo": 226.68, "avgVoc": 299.95, "avgPm2_5": 0.0, "avgPm10": 0.0, "avgDs18": 19.38, "samplxH": 38}, {"time": "2020-04-11_08", "missingData": "false", "avgTemp": 19.1, "avgCo2": 408.46, "avgRad": 44.44, "avg03": 9999.0, "avgNo2": 18.54, "avgCo": 236.97, "avgVoc": 305.3, "avgPm2_5": 0.0, "avgPm10": 0.0, "avgDs18": 23.52, "samplxH": 37}, {"time": "2020-04-11_09", "missingData": "false", "avgTemp": 21.83, "avgCo2": 405.85, "avgRad": 42.0, "avg03": 9999.0, "avgNo2": 19.31, "avgCo": 245.74, "avgVoc": 309.15, "avgPm2_5": 0.0, "avgPm10": 0.0, "avgDs18": 26.51, "samplxH": 39}, {"time": "2020-04-11_10", "missingData": "false", "avgTemp": 20.67, "avgCo2": 406.0, "avgRad": 45.16, "avg03": 9999.0, "avgNo2": 16.13, "avgCo": 246.95, "avgVoc": 296.32, "avgPm2_5": 0.0, "avgPm10": 0.0, "avgDs18": 26.14, "samplxH": 38}, {"time": "2020-04-11_11", "missingData": "false", "avgTemp": 22.17, "avgCo2": 402.88, "avgRad": 40.76, "avg03": 9999.0, "avgNo2": 12.35, "avgCo": 241.88, "avgVoc": 279.0, "avgPm2_5": 0.0, "avgPm10": 0.0, "avgDs18": 26.53, "samplxH": 40}, {"time": "2020-04-11_12", "missingData": "false", "avgTemp": 26.44, "avgCo2": 396.05, "avgRad": 27.51, "avg03": 9999.0, "avgNo2": 14.26, "avgCo": 219.03, "avgVoc": 279.08, "avgPm2_5": 0.0, "avgPm10": 0.0, "avgDs18": 31.02, "samplxH": 39}, {"time": "2020-04-11_13", "missingData": "false", "avgTemp": 24.9, "avgCo2": 397.41, "avgRad": 27.69, "avg03": 9999.0, "avgNo2": 12.87, "avgCo": 214.18, "avgVoc": 269.49, "avgPm2_5": 0.0, "avgPm10": 0.0, "avgDs18": 29.56, "samplxH": 39}, {"time": "2020-04-11_14", "missingData": "false", "avgTemp": 23.64, "avgCo2": 396.47, "avgRad": 31.76, "avg03": 9999.0, "avgNo2": 11.44, "avgCo": 223.14, "avgVoc": 266.44, "avgPm2_5": 0.0, "avgPm10": 0.0, "avgDs18": 27.99, "samplxH": 36}, {"time": "2020-04-11_15", "missingData": "false", "avgTemp": 22.75, "avgCo2": 396.94, "avgRad": 31.98, "avg03": 9999.0, "avgNo2": 10.76, "avgCo": 220.47, "avgVoc": 263.03, "avgPm2_5": 0.0, "avgPm10": 0.0, "avgDs18": 27.02, "samplxH": 34}, {"time": "2020-04-11_16", "missingData": "false", "avgTemp": 21.25, "avgCo2": 397.19, "avgRad": 33.72, "avg03": 9999.0, "avgNo2": 10.54, "avgCo": 220.89, "avgVoc": 265.22, "avgPm2_5": 0.0, "avgPm10": 0.0, "avgDs18": 25.44, "samplxH": 37}, {"time": "2020-04-11_17", "missingData": "false", "avgTemp": 18.7, "avgCo2": 403.98, "avgRad": 38.17, "avg03": 9999.0, "avgNo2": 12.95, "avgCo": 224.07, "avgVoc": 280.0, "avgPm2_5": 0.0, "avgPm10": 0.0, "avgDs18": 23.17, "samplxH": 40}, {"time": "2020-04-11_18", "missingData": "false", "avgTemp": 15.94, "avgCo2": 412.59, "avgRad": 41.68, "avg03": 9999.0, "avgNo2": 11.41, "avgCo": 220.54, "avgVoc": 276.18, "avgPm2_5": 0.0, "avgPm10": 0.0, "avgDs18": 20.66, "samplxH": 39}, {"time": "2020-04-11_19", "missingData": "false", "avgTemp": 14.42, "avgCo2": 417.9, "avgRad": 48.01, "avg03": 9999.0, "avgNo2": 12.77, "avgCo": 225.94, "avgVoc": 285.61, "avgPm2_5": 0.0, "avgPm10": 0.0, "avgDs18": 19.05, "samplxH": 31}, {"time": "2020-04-11_20", "missingData": "false", "avgTemp": 12.85, "avgCo2": 418.25, "avgRad": 51.88, "avg03": 9999.0, "avgNo2": 12.18, "avgCo": 221.71, "avgVoc": 284.75, "avgPm2_5": 0.0, "avgPm10": 0.0, "avgDs18": 17.44, "samplxH": 28}, {"time": "2020-04-11_21", "missingData": "false", "avgTemp": 11.26, "avgCo2": 429.49, "avgRad": 58.77, "avg03": 9999.0, "avgNo2": 14.19, "avgCo": 224.27, "avgVoc": 296.0, "avgPm2_5": 0.0, "avgPm10": 0.0, "avgDs18": 15.95, "samplxH": 37}, {"time": "2020-04-11_22", "missingData": "false", "avgTemp": 10.04, "avgCo2": 432.43, "avgRad": 63.72, "avg03": 9999.0, "avgNo2": 14.28, "avgCo": 223.7, "avgVoc": 296.77, "avgPm2_5": 0.0, "avgPm10": 0.0, "avgDs18": 14.7, "samplxH": 40}, {"time": "2020-04-11_23", "missingData": "false", "avgTemp": 8.86, "avgCo2": 429.79, "avgRad": 68.08, "avg03": 9999.0, "avgNo2": 17.12, "avgCo": 209.82, "avgVoc": 280.41, "avgPm2_5": 0.0, "avgPm10": 0.0, "avgDs18": 13.28, "samplxH": 34}]}