{"day": "2020-05-03", "latitude": 43.75264, "longitude": 11.231095, "avgDailyTemp": 22.94, "avgDailyCo2": 426.41, "avgDailyRad": 62.89, "avgDailyO3": 9999.0, "avgDailyNo2": 59.39, "avgDailyCo": 244.09, "avgDailyVoc": 330.04, "avgDailyPm2_5": 0.0, "avgDailyPm10": 0.0, "avgDailyDs18": 29.32, "data": [{"time": "2020-05-03_00", "missingData": "false", "avgTemp": 14.66, "avgCo2": 452.21, "avgRad": 99.9, "avg03": 9999.0, "avgNo2": 89.59, "avgCo": 242.34, "avgVoc": 316.14, "avgPm2_5": 0.0, "avgPm10": 0.0, "avgDs18": 19.56, "samplxH": 29}, {"time": "2020-05-03_01", "missingData": "true", "avgTemp": 0, "avgCo2": 0, "avgRad": 0, "avg03": 0, "avgNo2": 0, "avgCo": 0, "avgVoc": 0, "avgPm2_5": 0, "avgPm10": 0, "avgDs18": 0, "samplxH": 0}, {"time": "2020-05-03_02", "missingData": "true", "avgTemp": 0, "avgCo2": 0, "avgRad": 0, "avg03": 0, "avgNo2": 0, "avgCo": 0, "avgVoc": 0, "avgPm2_5": 0, "avgPm10": 0, "avgDs18": 0, "samplxH": 0}, {"time": "2020-05-03_03", "missingData": "true", "avgTemp": 0, "avgCo2": 0, "avgRad": 0, "avg03": 0, "avgNo2": 0, "avgCo": 0, "avgVoc": 0, "avgPm2_5": 0, "avgPm10": 0, "avgDs18": 0, "samplxH": 0}, {"time": "2020-05-03_04", "missingData": "true", "avgTemp": 0, "avgCo2": 0, "avgRad": 0, "avg03": 0, "avgNo2": 0, "avgCo": 0, "avgVoc": 0, "avgPm2_5": 0, "avgPm10": 0, "avgDs18": 0, "samplxH": 0}, {"time": "2020-05-03_05", "missingData": "true", "avgTemp": 0, "avgCo2": 0, "avgRad": 0, "avg03": 0, "avgNo2": 0, "avgCo": 0, "avgVoc": 0, "avgPm2_5": 0, "avgPm10": 0, "avgDs18": 0, "samplxH": 0}, {"time": "2020-05-03_06", "missingData": "true", "avgTemp": 0, "avgCo2": 0, "avgRad": 0, "avg03": 0, "avgNo2": 0, "avgCo": 0, "avgVoc": 0, "avgPm2_5": 0, "avgPm10": 0, "avgDs18": 0, "samplxH": 0}, {"time": "2020-05-03_07", "missingData": "true", "avgTemp": 0, "avgCo2": 0, "avgRad": 0, "avg03": 0, "avgNo2": 0, "avgCo": 0, "avgVoc": 0, "avgPm2_5": 0, "avgPm10": 0, "avgDs18": 0, "samplxH": 0}, {"time": "2020-05-03_08", "missingData": "true", "avgTemp": 0, "avgCo2": 0, "avgRad": 0, "avg03": 0, "avgNo2": 0, "avgCo": 0, "avgVoc": 0, "avgPm2_5": 0, "avgPm10": 0, "avgDs18": 0, "samplxH": 0}, {"time": "2020-05-03_09", "missingData": "true", "avgTemp": 0, "avgCo2": 0, "avgRad": 0, "avg03": 0, "avgNo2": 0, "avgCo": 0, "avgVoc": 0, "avgPm2_5": 0, "avgPm10": 0, "avgDs18": 0, "samplxH": 0}, {"time": "2020-05-03_10", "missingData": "true", "avgTemp": 0, "avgCo2": 0, "avgRad": 0, "avg03": 0, "avgNo2": 0, "avgCo": 0, "avgVoc": 0, "avgPm2_5": 0, "avgPm10": 0, "avgDs18": 0, "samplxH": 0}, {"time": "2020-05-03_11", "missingData": "false", "avgTemp": 26.67, "avgCo2": 413.5, "avgRad": 43.37, "avg03": 9999.0, "avgNo2": 36.0, "avgCo": 237.67, "avgVoc": 328.17, "avgPm2_5": 0.0, "avgPm10": 0.0, "avgDs18": 33.12, "samplxH": 6}, {"time": "2020-05-03_12", "missingData": "false", "avgTemp": 27.03, "avgCo2": 413.9, "avgRad": 44.75, "avg03": 9999.0, "avgNo2": 45.92, "avgCo": 246.26, "avgVoc": 338.64, "avgPm2_5": 0.0, "avgPm10": 0.0, "avgDs18": 34.26, "samplxH": 39}, {"time": "2020-05-03_13", "missingData": "false", "avgTemp": 27.37, "avgCo2": 412.33, "avgRad": 43.84, "avg03": 9999.0, "avgNo2": 43.93, "avgCo": 244.33, "avgVoc": 336.0, "avgPm2_5": 0.0, "avgPm10": 0.0, "avgDs18": 34.49, "samplxH": 15}, {"time": "2020-05-03_14", "missingData": "true", "avgTemp": 0, "avgCo2": 0, "avgRad": 0, "avg03": 0, "avgNo2": 0, "avgCo": 0, "avgVoc": 0, "avgPm2_5": 0, "avgPm10": 0, "avgDs18": 0, "samplxH": 0}, {"time": "2020-05-03_15", "missingData": "true", "avgTemp": 0, "avgCo2": 0, "avgRad": 0, "avg03": 0, "avgNo2": 0, "avgCo": 0, "avgVoc": 0, "avgPm2_5": 0, "avgPm10": 0, "avgDs18": 0, "samplxH": 0}, {"time": "2020-05-03_16", "missingData": "true", "avgTemp": 0, "avgCo2": 0, "avgRad": 0, "avg03": 0, "avgNo2": 0, "avgCo": 0, "avgVoc": 0, "avgPm2_5": 0, "avgPm10": 0, "avgDs18": 0, "samplxH": 0}, {"time": "2020-05-03_17", "missingData": "true", "avgTemp": 0, "avgCo2": 0, "avgRad": 0, "avg03": 0, "avgNo2": 0, "avgCo": 0, "avgVoc": 0, "avgPm2_5": 0, "avgPm10": 0, "avgDs18": 0, "samplxH": 0}, {"time": "2020-05-03_18", "missingData": "true", "avgTemp": 0, "avgCo2": 0, "avgRad": 0, "avg03": 0, "avgNo2": 0, "avgCo": 0, "avgVoc": 0, "avgPm2_5": 0, "avgPm10": 0, "avgDs18": 0, "samplxH": 0}, {"time": "2020-05-03_19", "missingData": "true", "avgTemp": 0, "avgCo2": 0, "avgRad": 0, "avg03": 0, "avgNo2": 0, "avgCo": 0, "avgVoc": 0, "avgPm2_5": 0, "avgPm10": 0, "avgDs18": 0, "samplxH": 0}, {"time": "2020-05-03_20", "missingData": "true", "avgTemp": 0, "avgCo2": 0, "avgRad": 0, "avg03": 0, "avgNo2": 0, "avgCo": 0, "avgVoc": 0, "avgPm2_5": 0, "avgPm10": 0, "avgDs18": 0, "samplxH": 0}, {"time": "2020-05-03_21", "missingData": "true", "avgTemp": 0, "avgCo2": 0, "avgRad": 0, "avg03": 0, "avgNo2": 0, "avgCo": 0, "avgVoc": 0, "avgPm2_5": 0, "avgPm10": 0, "avgDs18": 0, "samplxH": 0}, {"time": "2020-05-03_22", "missingData": "true", "avgTemp": 0, "avgCo2": 0, "avgRad": 0, "avg03": 0, "avgNo2": 0, "avgCo": 0, "avgVoc": 0, "avgPm2_5": 0, "avgPm10": 0, "avgDs18": 0, "samplxH": 0}, {"time": "2020-05-03_23", "missingData": "true", "avgTemp": 0, "avgCo2": 0, "avgRad": 0, "avg03": 0, "avgNo2": 0, "avgCo": 0, "avgVoc": 0, "avgPm2_5": 0, "avgPm10": 0, "avgDs18": 0, "samplxH": 0}]}