{"day": "2020-03-19", "latitude": 43.788262, "longitude": 11.2267015, "avgDailyTemp": 17.04, "avgDailyCo2": 3087.33, "avgDailyRad": 48.4, "avgDailyO3": 41.34, "avgDailyNo2": 109.99, "avgDailyCo": 209.02, "avgDailyVoc": 823.66, "avgDailyPm2_5": 12.49, "avgDailyPm10": 4.28, "avgDailyDs18": 27.41, "data": [{"time": "2020-03-19_00", "missingData": "false", "avgTemp": 14.84, "avgCo2": 1583.14, "avgRad": 54.67, "avg03": 50.41, "avgNo2": 100.97, "avgCo": 202.79, "avgVoc": 793.48, "avgPm2_5": 16.0, "avgPm10": 6.69, "avgDs18": 25.66, "samplxH": 29}, {"time": "2020-03-19_01", "missingData": "false", "avgTemp": 13.57, "avgCo2": 2367.64, "avgRad": 58.38, "avg03": 44.08, "avgNo2": 102.11, "avgCo": 200.14, "avgVoc": 793.33, "avgPm2_5": 15.75, "avgPm10": 6.44, "avgDs18": 24.5, "samplxH": 36}, {"time": "2020-03-19_02", "missingData": "false", "avgTemp": 12.84, "avgCo2": 3572.73, "avgRad": 60.39, "avg03": 38.36, "avgNo2": 104.58, "avgCo": 214.73, "avgVoc": 832.48, "avgPm2_5": 13.39, "avgPm10": 5.06, "avgDs18": 23.97, "samplxH": 33}, {"time": "2020-03-19_03", "missingData": "false", "avgTemp": 12.27, "avgCo2": 2326.03, "avgRad": 60.75, "avg03": 36.84, "avgNo2": 102.71, "avgCo": 207.13, "avgVoc": 821.68, "avgPm2_5": 11.71, "avgPm10": 4.16, "avgDs18": 23.41, "samplxH": 31}, {"time": "2020-03-19_04", "missingData": "false", "avgTemp": 11.65, "avgCo2": 3275.97, "avgRad": 62.71, "avg03": 36.69, "avgNo2": 109.97, "avgCo": 199.72, "avgVoc": 808.16, "avgPm2_5": 11.69, "avgPm10": 4.09, "avgDs18": 23.02, "samplxH": 32}, {"time": "2020-03-19_05", "missingData": "false", "avgTemp": 11.04, "avgCo2": 1968.77, "avgRad": 64.54, "avg03": 28.8, "avgNo2": 132.6, "avgCo": 215.57, "avgVoc": 895.5, "avgPm2_5": 11.5, "avgPm10": 3.8, "avgDs18": 22.59, "samplxH": 30}, {"time": "2020-03-19_06", "missingData": "false", "avgTemp": 11.46, "avgCo2": 3171.03, "avgRad": 63.5, "avg03": 25.32, "avgNo2": 149.19, "avgCo": 231.35, "avgVoc": 939.97, "avgPm2_5": 12.97, "avgPm10": 4.52, "avgDs18": 22.79, "samplxH": 31}, {"time": "2020-03-19_07", "missingData": "false", "avgTemp": 13.32, "avgCo2": 3276.3, "avgRad": 58.58, "avg03": 25.57, "avgNo2": 152.97, "avgCo": 220.27, "avgVoc": 911.83, "avgPm2_5": 13.87, "avgPm10": 5.47, "avgDs18": 24.06, "samplxH": 30}, {"time": "2020-03-19_08", "missingData": "false", "avgTemp": 15.42, "avgCo2": 3163.83, "avgRad": 53.06, "avg03": 29.03, "avgNo2": 135.34, "avgCo": 212.62, "avgVoc": 867.28, "avgPm2_5": 14.55, "avgPm10": 5.52, "avgDs18": 25.69, "samplxH": 29}, {"time": "2020-03-19_09", "missingData": "false", "avgTemp": 18.7, "avgCo2": 3886.09, "avgRad": 44.38, "avg03": 39.09, "avgNo2": 104.66, "avgCo": 210.25, "avgVoc": 803.94, "avgPm2_5": 11.69, "avgPm10": 3.91, "avgDs18": 28.15, "samplxH": 32}, {"time": "2020-03-19_10", "missingData": "false", "avgTemp": 20.79, "avgCo2": 4859.61, "avgRad": 38.5, "avg03": 42.19, "avgNo2": 102.68, "avgCo": 213.19, "avgVoc": 803.9, "avgPm2_5": 10.55, "avgPm10": 2.68, "avgDs18": 30.1, "samplxH": 31}, {"time": "2020-03-19_11", "missingData": "false", "avgTemp": 22.17, "avgCo2": 6094.93, "avgRad": 31.43, "avg03": 50.66, "avgNo2": 89.1, "avgCo": 202.59, "avgVoc": 780.97, "avgPm2_5": 10.69, "avgPm10": 2.9, "avgDs18": 31.29, "samplxH": 29}, {"time": "2020-03-19_12", "missingData": "false", "avgTemp": 22.96, "avgCo2": 3495.43, "avgRad": 28.39, "avg03": 51.6, "avgNo2": 91.47, "avgCo": 200.5, "avgVoc": 789.57, "avgPm2_5": 10.03, "avgPm10": 2.5, "avgDs18": 31.99, "samplxH": 30}, {"time": "2020-03-19_13", "missingData": "false", "avgTemp": 23.52, "avgCo2": 2383.58, "avgRad": 25.64, "avg03": 51.39, "avgNo2": 89.45, "avgCo": 196.85, "avgVoc": 791.79, "avgPm2_5": 9.52, "avgPm10": 2.0, "avgDs18": 32.52, "samplxH": 33}, {"time": "2020-03-19_14", "missingData": "false", "avgTemp": 25.02, "avgCo2": 5498.4, "avgRad": 26.08, "avg03": 53.12, "avgNo2": 92.96, "avgCo": 201.0, "avgVoc": 790.88, "avgPm2_5": 10.24, "avgPm10": 2.76, "avgDs18": 33.84, "samplxH": 25}, {"time": "2020-03-19_15", "missingData": "false", "avgTemp": 24.74, "avgCo2": 4857.48, "avgRad": 27.09, "avg03": 49.26, "avgNo2": 97.04, "avgCo": 202.93, "avgVoc": 797.7, "avgPm2_5": 10.41, "avgPm10": 2.63, "avgDs18": 34.23, "samplxH": 27}, {"time": "2020-03-19_16", "missingData": "false", "avgTemp": 22.74, "avgCo2": 67.05, "avgRad": 32.73, "avg03": 52.57, "avgNo2": 91.95, "avgCo": 203.05, "avgVoc": 786.24, "avgPm2_5": 10.86, "avgPm10": 2.86, "avgDs18": 32.45, "samplxH": 21}, {"time": "2020-03-19_17", "missingData": "false", "avgTemp": 20.18, "avgCo2": 74.9, "avgRad": 40.91, "avg03": 52.33, "avgNo2": 90.71, "avgCo": 207.1, "avgVoc": 780.57, "avgPm2_5": 11.38, "avgPm10": 3.43, "avgDs18": 30.22, "samplxH": 21}, {"time": "2020-03-19_18", "missingData": "false", "avgTemp": 18.5, "avgCo2": 3469.24, "avgRad": 44.74, "avg03": 55.35, "avgNo2": 86.35, "avgCo": 205.59, "avgVoc": 774.0, "avgPm2_5": 12.41, "avgPm10": 4.18, "avgDs18": 28.66, "samplxH": 17}, {"time": "2020-03-19_19", "missingData": "false", "avgTemp": 18.01, "avgCo2": 4094.21, "avgRad": 46.09, "avg03": 58.08, "avgNo2": 86.67, "avgCo": 207.92, "avgVoc": 775.42, "avgPm2_5": 12.04, "avgPm10": 4.04, "avgDs18": 28.26, "samplxH": 24}, {"time": "2020-03-19_20", "missingData": "false", "avgTemp": 16.79, "avgCo2": 682.76, "avgRad": 50.56, "avg03": 38.59, "avgNo2": 134.14, "avgCo": 203.34, "avgVoc": 823.21, "avgPm2_5": 13.69, "avgPm10": 5.17, "avgDs18": 27.35, "samplxH": 29}, {"time": "2020-03-19_21", "missingData": "false", "avgTemp": 16.03, "avgCo2": 3389.72, "avgRad": 53.88, "avg03": 32.31, "avgNo2": 133.21, "avgCo": 217.34, "avgVoc": 868.59, "avgPm2_5": 14.9, "avgPm10": 5.76, "avgDs18": 27.1, "samplxH": 29}, {"time": "2020-03-19_22", "missingData": "false", "avgTemp": 15.06, "avgCo2": 2186.53, "avgRad": 56.81, "avg03": 34.93, "avgNo2": 114.6, "avgCo": 223.73, "avgVoc": 856.07, "avgPm2_5": 14.07, "avgPm10": 5.37, "avgDs18": 26.35, "samplxH": 30}, {"time": "2020-03-19_23", "missingData": "false", "avgTemp": 14.47, "avgCo2": 3458.39, "avgRad": 58.76, "avg03": 35.33, "avgNo2": 117.61, "avgCo": 212.17, "avgVoc": 825.67, "avgPm2_5": 14.06, "avgPm10": 5.36, "avgDs18": 25.64, "samplxH": 36}]}