{"day": "2020-07-05", "latitude": 43.7996609, "longitude": 11.2440115, "avgDailyTemp": 27.08, "avgDailyCo2": 409.42, "avgDailyRad": 49.14, "avgDailyO3": 9999.0, "avgDailyNo2": 208.92, "avgDailyCo": 247.69, "avgDailyVoc": 498.7, "avgDailyPm2_5": 999.0, "avgDailyPm10": 999.0, "avgDailyDs18": 43.02, "data": [{"time": "2020-07-05_00", "missingData": "false", "avgTemp": 22.39, "avgCo2": 414.95, "avgRad": 67.42, "avg03": 9999.0, "avgNo2": 204.08, "avgCo": 252.34, "avgVoc": 492.87, "avgPm2_5": 999.0, "avgPm10": 999.0, "avgDs18": 36.99, "samplxH": 38}, {"time": "2020-07-05_01", "missingData": "false", "avgTemp": 20.65, "avgCo2": 421.21, "avgRad": 74.5, "avg03": 9999.0, "avgNo2": 205.29, "avgCo": 248.95, "avgVoc": 493.08, "avgPm2_5": 999.0, "avgPm10": 999.0, "avgDs18": 35.56, "samplxH": 38}, {"time": "2020-07-05_02", "missingData": "false", "avgTemp": 20.05, "avgCo2": 430.0, "avgRad": 77.75, "avg03": 9999.0, "avgNo2": 220.74, "avgCo": 248.03, "avgVoc": 500.05, "avgPm2_5": 999.0, "avgPm10": 999.0, "avgDs18": 34.79, "samplxH": 39}, {"time": "2020-07-05_03", "missingData": "false", "avgTemp": 18.83, "avgCo2": 434.95, "avgRad": 82.83, "avg03": 9999.0, "avgNo2": 222.85, "avgCo": 244.75, "avgVoc": 500.6, "avgPm2_5": 999.0, "avgPm10": 999.0, "avgDs18": 33.75, "samplxH": 40}, {"time": "2020-07-05_04", "missingData": "false", "avgTemp": 19.31, "avgCo2": 435.79, "avgRad": 80.14, "avg03": 9999.0, "avgNo2": 229.64, "avgCo": 245.54, "avgVoc": 505.05, "avgPm2_5": 999.0, "avgPm10": 999.0, "avgDs18": 34.07, "samplxH": 39}, {"time": "2020-07-05_05", "missingData": "false", "avgTemp": 20.93, "avgCo2": 430.93, "avgRad": 72.09, "avg03": 9999.0, "avgNo2": 227.78, "avgCo": 248.85, "avgVoc": 506.6, "avgPm2_5": 999.0, "avgPm10": 999.0, "avgDs18": 35.81, "samplxH": 40}, {"time": "2020-07-05_06", "missingData": "false", "avgTemp": 24.78, "avgCo2": 424.0, "avgRad": 56.62, "avg03": 9999.0, "avgNo2": 228.12, "avgCo": 251.8, "avgVoc": 510.45, "avgPm2_5": 999.0, "avgPm10": 999.0, "avgDs18": 39.96, "samplxH": 40}, {"time": "2020-07-05_07", "missingData": "false", "avgTemp": 28.42, "avgCo2": 416.43, "avgRad": 43.97, "avg03": 9999.0, "avgNo2": 226.65, "avgCo": 254.03, "avgVoc": 513.62, "avgPm2_5": 999.0, "avgPm10": 999.0, "avgDs18": 45.44, "samplxH": 37}, {"time": "2020-07-05_08", "missingData": "false", "avgTemp": 29.59, "avgCo2": 395.25, "avgRad": 35.49, "avg03": 9999.0, "avgNo2": 198.05, "avgCo": 240.95, "avgVoc": 498.68, "avgPm2_5": 999.0, "avgPm10": 999.0, "avgDs18": 46.44, "samplxH": 40}, {"time": "2020-07-05_09", "missingData": "false", "avgTemp": 31.0, "avgCo2": 395.95, "avgRad": 34.49, "avg03": 9999.0, "avgNo2": 206.82, "avgCo": 246.9, "avgVoc": 503.18, "avgPm2_5": 999.0, "avgPm10": 999.0, "avgDs18": 48.21, "samplxH": 39}, {"time": "2020-07-05_10", "missingData": "false", "avgTemp": 31.28, "avgCo2": 395.61, "avgRad": 33.11, "avg03": 9999.0, "avgNo2": 218.58, "avgCo": 241.61, "avgVoc": 503.19, "avgPm2_5": 999.0, "avgPm10": 999.0, "avgDs18": 47.87, "samplxH": 31}, {"time": "2020-07-05_11", "missingData": "false", "avgTemp": 32.28, "avgCo2": 397.54, "avgRad": 31.37, "avg03": 9999.0, "avgNo2": 220.62, "avgCo": 244.31, "avgVoc": 506.87, "avgPm2_5": 999.0, "avgPm10": 999.0, "avgDs18": 50.23, "samplxH": 39}, {"time": "2020-07-05_12", "missingData": "false", "avgTemp": 32.64, "avgCo2": 397.77, "avgRad": 31.49, "avg03": 9999.0, "avgNo2": 214.62, "avgCo": 247.59, "avgVoc": 505.03, "avgPm2_5": 999.0, "avgPm10": 999.0, "avgDs18": 50.86, "samplxH": 39}, {"time": "2020-07-05_13", "missingData": "false", "avgTemp": 33.3, "avgCo2": 398.86, "avgRad": 30.66, "avg03": 9999.0, "avgNo2": 214.89, "avgCo": 249.81, "avgVoc": 506.06, "avgPm2_5": 999.0, "avgPm10": 999.0, "avgDs18": 51.77, "samplxH": 36}, {"time": "2020-07-05_14", "missingData": "false", "avgTemp": 33.29, "avgCo2": 399.85, "avgRad": 30.89, "avg03": 9999.0, "avgNo2": 211.26, "avgCo": 251.03, "avgVoc": 503.67, "avgPm2_5": 999.0, "avgPm10": 999.0, "avgDs18": 51.76, "samplxH": 39}, {"time": "2020-07-05_15", "missingData": "false", "avgTemp": 33.44, "avgCo2": 397.81, "avgRad": 30.93, "avg03": 9999.0, "avgNo2": 209.86, "avgCo": 252.0, "avgVoc": 502.7, "avgPm2_5": 999.0, "avgPm10": 999.0, "avgDs18": 51.25, "samplxH": 37}, {"time": "2020-07-05_16", "missingData": "false", "avgTemp": 32.76, "avgCo2": 396.11, "avgRad": 31.86, "avg03": 9999.0, "avgNo2": 203.38, "avgCo": 250.97, "avgVoc": 497.97, "avgPm2_5": 999.0, "avgPm10": 999.0, "avgDs18": 50.17, "samplxH": 37}, {"time": "2020-07-05_17", "missingData": "false", "avgTemp": 31.5, "avgCo2": 395.0, "avgRad": 34.44, "avg03": 9999.0, "avgNo2": 194.46, "avgCo": 249.63, "avgVoc": 491.17, "avgPm2_5": 999.0, "avgPm10": 999.0, "avgDs18": 47.01, "samplxH": 35}, {"time": "2020-07-05_18", "missingData": "false", "avgTemp": 30.27, "avgCo2": 395.29, "avgRad": 36.88, "avg03": 9999.0, "avgNo2": 194.63, "avgCo": 249.13, "avgVoc": 490.58, "avgPm2_5": 999.0, "avgPm10": 999.0, "avgDs18": 45.21, "samplxH": 38}, {"time": "2020-07-05_19", "missingData": "false", "avgTemp": 28.38, "avgCo2": 397.25, "avgRad": 40.62, "avg03": 9999.0, "avgNo2": 187.61, "avgCo": 246.19, "avgVoc": 485.42, "avgPm2_5": 999.0, "avgPm10": 999.0, "avgDs18": 42.47, "samplxH": 36}, {"time": "2020-07-05_20", "missingData": "false", "avgTemp": 27.15, "avgCo2": 401.19, "avgRad": 43.48, "avg03": 9999.0, "avgNo2": 186.05, "avgCo": 246.51, "avgVoc": 485.11, "avgPm2_5": 999.0, "avgPm10": 999.0, "avgDs18": 41.34, "samplxH": 37}, {"time": "2020-07-05_21", "missingData": "false", "avgTemp": 24.87, "avgCo2": 408.53, "avgRad": 50.39, "avg03": 9999.0, "avgNo2": 188.0, "avgCo": 244.39, "avgVoc": 485.13, "avgPm2_5": 999.0, "avgPm10": 999.0, "avgDs18": 39.48, "samplxH": 38}, {"time": "2020-07-05_22", "missingData": "false", "avgTemp": 23.27, "avgCo2": 416.58, "avgRad": 57.24, "avg03": 9999.0, "avgNo2": 196.58, "avgCo": 245.0, "avgVoc": 489.32, "avgPm2_5": 999.0, "avgPm10": 999.0, "avgDs18": 37.98, "samplxH": 38}, {"time": "2020-07-05_23", "missingData": "false", "avgTemp": 22.16, "avgCo2": 420.92, "avgRad": 61.26, "avg03": 9999.0, "avgNo2": 199.95, "avgCo": 243.95, "avgVoc": 490.77, "avgPm2_5": 999.0, "avgPm10": 999.0, "avgDs18": 36.82, "samplxH": 39}]}