{"day": "2020-03-01", "latitude": 43.7744583, "longitude": 11.255065, "avgDailyTemp": 12.62, "avgDailyCo2": 407.0, "avgDailyRad": 85.59, "avgDailyO3": 229.75, "avgDailyNo2": 78.63, "avgDailyCo": 299.03, "avgDailyVoc": 351.59, "avgDailyPm2_5": 63.45, "avgDailyPm10": 12.39, "avgDailyDs18": 22.03, "data": [{"time": "2020-03-01_00", "missingData": "false", "avgTemp": 11.63, "avgCo2": 412.82, "avgRad": 80.18, "avg03": 124.09, "avgNo2": 76.74, "avgCo": 292.38, "avgVoc": 358.74, "avgPm2_5": 54.62, "avgPm10": 10.12, "avgDs18": 21.38, "samplxH": 34}, {"time": "2020-03-01_01", "missingData": "false", "avgTemp": 12.01, "avgCo2": 402.94, "avgRad": 78.82, "avg03": 244.24, "avgNo2": 69.3, "avgCo": 289.76, "avgVoc": 347.27, "avgPm2_5": 53.97, "avgPm10": 9.18, "avgDs18": 21.69, "samplxH": 33}, {"time": "2020-03-01_02", "missingData": "false", "avgTemp": 12.01, "avgCo2": 403.86, "avgRad": 77.21, "avg03": 250.0, "avgNo2": 68.94, "avgCo": 285.19, "avgVoc": 344.47, "avgPm2_5": 50.25, "avgPm10": 8.69, "avgDs18": 21.83, "samplxH": 36}, {"time": "2020-03-01_03", "missingData": "false", "avgTemp": 11.88, "avgCo2": 406.5, "avgRad": 78.3, "avg03": 250.0, "avgNo2": 70.92, "avgCo": 284.36, "avgVoc": 345.53, "avgPm2_5": 52.72, "avgPm10": 9.17, "avgDs18": 21.79, "samplxH": 36}, {"time": "2020-03-01_04", "missingData": "false", "avgTemp": 11.92, "avgCo2": 408.94, "avgRad": 79.92, "avg03": 249.79, "avgNo2": 73.47, "avgCo": 285.53, "avgVoc": 348.65, "avgPm2_5": 56.09, "avgPm10": 9.56, "avgDs18": 21.7, "samplxH": 34}, {"time": "2020-03-01_05", "missingData": "false", "avgTemp": 12.07, "avgCo2": 410.5, "avgRad": 80.26, "avg03": 250.0, "avgNo2": 73.36, "avgCo": 285.25, "avgVoc": 349.14, "avgPm2_5": 58.22, "avgPm10": 10.06, "avgDs18": 21.72, "samplxH": 36}, {"time": "2020-03-01_06", "missingData": "false", "avgTemp": 12.23, "avgCo2": 411.53, "avgRad": 80.89, "avg03": 238.74, "avgNo2": 77.38, "avgCo": 288.59, "avgVoc": 353.68, "avgPm2_5": 60.88, "avgPm10": 10.44, "avgDs18": 21.89, "samplxH": 34}, {"time": "2020-03-01_07", "missingData": "false", "avgTemp": 13.29, "avgCo2": 416.16, "avgRad": 80.79, "avg03": 183.54, "avgNo2": 83.51, "avgCo": 296.38, "avgVoc": 362.54, "avgPm2_5": 73.76, "avgPm10": 12.76, "avgDs18": 23.08, "samplxH": 37}, {"time": "2020-03-01_08", "missingData": "false", "avgTemp": 14.58, "avgCo2": 405.81, "avgRad": 78.0, "avg03": 250.0, "avgNo2": 76.54, "avgCo": 292.43, "avgVoc": 348.22, "avgPm2_5": 76.08, "avgPm10": 13.0, "avgDs18": 24.41, "samplxH": 37}, {"time": "2020-03-01_09", "missingData": "false", "avgTemp": 14.62, "avgCo2": 397.08, "avgRad": 78.17, "avg03": 250.0, "avgNo2": 77.64, "avgCo": 294.5, "avgVoc": 345.72, "avgPm2_5": 85.44, "avgPm10": 14.11, "avgDs18": 24.43, "samplxH": 36}, {"time": "2020-03-01_10", "missingData": "false", "avgTemp": 14.71, "avgCo2": 400.27, "avgRad": 80.62, "avg03": 250.0, "avgNo2": 81.07, "avgCo": 298.37, "avgVoc": 349.1, "avgPm2_5": 74.33, "avgPm10": 13.53, "avgDs18": 24.31, "samplxH": 30}, {"time": "2020-03-01_11", "missingData": "false", "avgTemp": 15.77, "avgCo2": 404.77, "avgRad": 75.84, "avg03": 250.0, "avgNo2": 85.74, "avgCo": 296.94, "avgVoc": 350.86, "avgPm2_5": 69.34, "avgPm10": 12.74, "avgDs18": 25.98, "samplxH": 35}, {"time": "2020-03-01_12", "missingData": "false", "avgTemp": 14.38, "avgCo2": 410.54, "avgRad": 86.32, "avg03": 247.23, "avgNo2": 88.34, "avgCo": 305.0, "avgVoc": 355.06, "avgPm2_5": 83.51, "avgPm10": 16.49, "avgDs18": 23.85, "samplxH": 35}, {"time": "2020-03-01_13", "missingData": "false", "avgTemp": 13.89, "avgCo2": 409.0, "avgRad": 88.31, "avg03": 240.14, "avgNo2": 89.31, "avgCo": 307.66, "avgVoc": 357.45, "avgPm2_5": 84.86, "avgPm10": 17.34, "avgDs18": 23.14, "samplxH": 29}, {"time": "2020-03-01_14", "missingData": "false", "avgTemp": 12.65, "avgCo2": 407.69, "avgRad": 97.39, "avg03": 165.37, "avgNo2": 97.2, "avgCo": 322.8, "avgVoc": 367.94, "avgPm2_5": 80.8, "avgPm10": 18.86, "avgDs18": 21.9, "samplxH": 35}, {"time": "2020-03-01_15", "missingData": "false", "avgTemp": 12.21, "avgCo2": 407.06, "avgRad": 94.84, "avg03": 226.83, "avgNo2": 81.51, "avgCo": 315.83, "avgVoc": 355.63, "avgPm2_5": 57.37, "avgPm10": 11.57, "avgDs18": 21.09, "samplxH": 35}, {"time": "2020-03-01_16", "missingData": "false", "avgTemp": 11.71, "avgCo2": 412.76, "avgRad": 95.17, "avg03": 190.15, "avgNo2": 88.76, "avgCo": 316.18, "avgVoc": 362.33, "avgPm2_5": 64.97, "avgPm10": 13.88, "avgDs18": 20.7, "samplxH": 33}, {"time": "2020-03-01_17", "missingData": "false", "avgTemp": 11.24, "avgCo2": 410.78, "avgRad": 97.68, "avg03": 180.27, "avgNo2": 83.57, "avgCo": 319.86, "avgVoc": 361.0, "avgPm2_5": 43.86, "avgPm10": 10.57, "avgDs18": 20.24, "samplxH": 37}, {"time": "2020-03-01_18", "missingData": "false", "avgTemp": 11.18, "avgCo2": 405.15, "avgRad": 96.97, "avg03": 242.3, "avgNo2": 78.3, "avgCo": 309.24, "avgVoc": 352.3, "avgPm2_5": 43.15, "avgPm10": 12.33, "avgDs18": 19.97, "samplxH": 33}, {"time": "2020-03-01_19", "missingData": "false", "avgTemp": 11.29, "avgCo2": 403.71, "avgRad": 95.48, "avg03": 237.06, "avgNo2": 80.32, "avgCo": 307.61, "avgVoc": 353.87, "avgPm2_5": 46.81, "avgPm10": 12.0, "avgDs18": 20.13, "samplxH": 31}, {"time": "2020-03-01_20", "missingData": "false", "avgTemp": 11.59, "avgCo2": 408.83, "avgRad": 92.94, "avg03": 250.06, "avgNo2": 77.37, "avgCo": 302.77, "avgVoc": 349.83, "avgPm2_5": 58.49, "avgPm10": 17.37, "avgDs18": 20.37, "samplxH": 35}, {"time": "2020-03-01_21", "missingData": "false", "avgTemp": 11.62, "avgCo2": 402.79, "avgRad": 90.09, "avg03": 250.0, "avgNo2": 72.0, "avgCo": 299.65, "avgVoc": 343.71, "avgPm2_5": 55.41, "avgPm10": 10.21, "avgDs18": 20.39, "samplxH": 34}, {"time": "2020-03-01_22", "missingData": "false", "avgTemp": 12.06, "avgCo2": 402.0, "avgRad": 87.74, "avg03": 250.0, "avgNo2": 69.35, "avgCo": 296.29, "avgVoc": 339.41, "avgPm2_5": 68.59, "avgPm10": 11.94, "avgDs18": 21.06, "samplxH": 34}, {"time": "2020-03-01_23", "missingData": "false", "avgTemp": 12.46, "avgCo2": 405.2, "avgRad": 84.39, "avg03": 250.0, "avgNo2": 68.46, "avgCo": 287.26, "avgVoc": 336.26, "avgPm2_5": 70.34, "avgPm10": 12.4, "avgDs18": 21.57, "samplxH": 35}]}