{"day": "2020-03-23", "latitude": 43.7996974, "longitude": 11.2440324, "avgDailyTemp": 7.04, "avgDailyCo2": 409.85, "avgDailyRad": 30.26, "avgDailyO3": 9999.0, "avgDailyNo2": 56.94, "avgDailyCo": 160.44, "avgDailyVoc": 404.62, "avgDailyPm2_5": 999.0, "avgDailyPm10": 999.0, "avgDailyDs18": 23.03, "data": [{"time": "2020-03-23_00", "missingData": "false", "avgTemp": 7.99, "avgCo2": 405.87, "avgRad": 43.61, "avg03": 9999.0, "avgNo2": 72.08, "avgCo": 177.51, "avgVoc": 407.31, "avgPm2_5": 999.0, "avgPm10": 999.0, "avgDs18": 23.25, "samplxH": 39}, {"time": "2020-03-23_01", "missingData": "false", "avgTemp": 7.52, "avgCo2": 405.15, "avgRad": 41.61, "avg03": 9999.0, "avgNo2": 67.67, "avgCo": 173.87, "avgVoc": 405.33, "avgPm2_5": 999.0, "avgPm10": 999.0, "avgDs18": 22.77, "samplxH": 39}, {"time": "2020-03-23_02", "missingData": "false", "avgTemp": 6.87, "avgCo2": 405.91, "avgRad": 41.79, "avg03": 9999.0, "avgNo2": 69.74, "avgCo": 170.14, "avgVoc": 405.03, "avgPm2_5": 999.0, "avgPm10": 999.0, "avgDs18": 21.39, "samplxH": 35}, {"time": "2020-03-23_03", "missingData": "false", "avgTemp": 6.4, "avgCo2": 406.54, "avgRad": 43.96, "avg03": 9999.0, "avgNo2": 72.68, "avgCo": 170.65, "avgVoc": 406.65, "avgPm2_5": 999.0, "avgPm10": 999.0, "avgDs18": 21.59, "samplxH": 37}, {"time": "2020-03-23_04", "missingData": "false", "avgTemp": 5.97, "avgCo2": 407.72, "avgRad": 45.36, "avg03": 9999.0, "avgNo2": 72.28, "avgCo": 172.05, "avgVoc": 410.1, "avgPm2_5": 999.0, "avgPm10": 999.0, "avgDs18": 21.22, "samplxH": 39}, {"time": "2020-03-23_05", "missingData": "false", "avgTemp": 5.56, "avgCo2": 408.69, "avgRad": 42.75, "avg03": 9999.0, "avgNo2": 67.51, "avgCo": 169.11, "avgVoc": 406.14, "avgPm2_5": 999.0, "avgPm10": 999.0, "avgDs18": 20.85, "samplxH": 35}, {"time": "2020-03-23_06", "missingData": "false", "avgTemp": 6.16, "avgCo2": 410.28, "avgRad": 38.67, "avg03": 9999.0, "avgNo2": 68.17, "avgCo": 167.97, "avgVoc": 411.47, "avgPm2_5": 999.0, "avgPm10": 999.0, "avgDs18": 22.14, "samplxH": 36}, {"time": "2020-03-23_07", "missingData": "false", "avgTemp": 6.89, "avgCo2": 409.79, "avgRad": 33.7, "avg03": 9999.0, "avgNo2": 64.91, "avgCo": 164.44, "avgVoc": 410.24, "avgPm2_5": 999.0, "avgPm10": 999.0, "avgDs18": 23.7, "samplxH": 34}, {"time": "2020-03-23_08", "missingData": "false", "avgTemp": 7.09, "avgCo2": 409.66, "avgRad": 30.24, "avg03": 9999.0, "avgNo2": 60.34, "avgCo": 160.77, "avgVoc": 406.74, "avgPm2_5": 999.0, "avgPm10": 999.0, "avgDs18": 23.35, "samplxH": 35}, {"time": "2020-03-23_09", "missingData": "false", "avgTemp": 7.95, "avgCo2": 409.39, "avgRad": 24.29, "avg03": 9999.0, "avgNo2": 56.5, "avgCo": 155.79, "avgVoc": 404.96, "avgPm2_5": 999.0, "avgPm10": 999.0, "avgDs18": 25.3, "samplxH": 28}, {"time": "2020-03-23_10", "missingData": "false", "avgTemp": 8.49, "avgCo2": 408.41, "avgRad": 18.93, "avg03": 9999.0, "avgNo2": 49.45, "avgCo": 149.41, "avgVoc": 400.36, "avgPm2_5": 999.0, "avgPm10": 999.0, "avgDs18": 26.22, "samplxH": 22}, {"time": "2020-03-23_11", "missingData": "false", "avgTemp": 8.84, "avgCo2": 408.94, "avgRad": 16.56, "avg03": 9999.0, "avgNo2": 46.86, "avgCo": 147.33, "avgVoc": 399.19, "avgPm2_5": 999.0, "avgPm10": 999.0, "avgDs18": 27.0, "samplxH": 36}, {"time": "2020-03-23_12", "missingData": "false", "avgTemp": 9.75, "avgCo2": 411.16, "avgRad": 14.27, "avg03": 9999.0, "avgNo2": 49.62, "avgCo": 146.97, "avgVoc": 405.59, "avgPm2_5": 999.0, "avgPm10": 999.0, "avgDs18": 28.2, "samplxH": 32}, {"time": "2020-03-23_13", "missingData": "false", "avgTemp": 10.28, "avgCo2": 412.0, "avgRad": 13.57, "avg03": 9999.0, "avgNo2": 50.45, "avgCo": 147.38, "avgVoc": 406.28, "avgPm2_5": 999.0, "avgPm10": 999.0, "avgDs18": 29.28, "samplxH": 29}, {"time": "2020-03-23_14", "missingData": "false", "avgTemp": 10.0, "avgCo2": 411.0, "avgRad": 14.06, "avg03": 9999.0, "avgNo2": 46.92, "avgCo": 147.36, "avgVoc": 400.48, "avgPm2_5": 999.0, "avgPm10": 999.0, "avgDs18": 27.73, "samplxH": 25}, {"time": "2020-03-23_15", "missingData": "false", "avgTemp": 9.71, "avgCo2": 411.6, "avgRad": 14.7, "avg03": 9999.0, "avgNo2": 45.44, "avgCo": 148.04, "avgVoc": 400.28, "avgPm2_5": 999.0, "avgPm10": 999.0, "avgDs18": 26.56, "samplxH": 25}, {"time": "2020-03-23_16", "missingData": "false", "avgTemp": 8.38, "avgCo2": 411.62, "avgRad": 16.78, "avg03": 9999.0, "avgNo2": 43.66, "avgCo": 148.24, "avgVoc": 398.17, "avgPm2_5": 999.0, "avgPm10": 999.0, "avgDs18": 24.84, "samplxH": 29}, {"time": "2020-03-23_17", "missingData": "false", "avgTemp": 6.82, "avgCo2": 411.94, "avgRad": 20.15, "avg03": 9999.0, "avgNo2": 41.81, "avgCo": 149.71, "avgVoc": 396.19, "avgPm2_5": 999.0, "avgPm10": 999.0, "avgDs18": 21.86, "samplxH": 31}, {"time": "2020-03-23_18", "missingData": "false", "avgTemp": 6.18, "avgCo2": 411.43, "avgRad": 22.23, "avg03": 9999.0, "avgNo2": 42.51, "avgCo": 151.51, "avgVoc": 398.03, "avgPm2_5": 999.0, "avgPm10": 999.0, "avgDs18": 21.07, "samplxH": 37}, {"time": "2020-03-23_19", "missingData": "false", "avgTemp": 5.71, "avgCo2": 412.18, "avgRad": 24.66, "avg03": 9999.0, "avgNo2": 47.05, "avgCo": 154.69, "avgVoc": 405.79, "avgPm2_5": 999.0, "avgPm10": 999.0, "avgDs18": 20.59, "samplxH": 39}, {"time": "2020-03-23_20", "missingData": "false", "avgTemp": 5.34, "avgCo2": 412.26, "avgRad": 27.52, "avg03": 9999.0, "avgNo2": 49.62, "avgCo": 156.53, "avgVoc": 404.53, "avgPm2_5": 999.0, "avgPm10": 999.0, "avgDs18": 20.31, "samplxH": 34}, {"time": "2020-03-23_21", "missingData": "false", "avgTemp": 5.12, "avgCo2": 412.56, "avgRad": 32.83, "avg03": 9999.0, "avgNo2": 50.71, "avgCo": 162.03, "avgVoc": 402.76, "avgPm2_5": 999.0, "avgPm10": 999.0, "avgDs18": 20.14, "samplxH": 34}, {"time": "2020-03-23_22", "missingData": "false", "avgTemp": 5.02, "avgCo2": 411.86, "avgRad": 37.44, "avg03": 9999.0, "avgNo2": 55.53, "avgCo": 167.14, "avgVoc": 405.17, "avgPm2_5": 999.0, "avgPm10": 999.0, "avgDs18": 20.06, "samplxH": 36}, {"time": "2020-03-23_23", "missingData": "false", "avgTemp": 4.58, "avgCo2": 412.76, "avgRad": 39.65, "avg03": 9999.0, "avgNo2": 56.49, "avgCo": 168.14, "avgVoc": 407.41, "avgPm2_5": 999.0, "avgPm10": 999.0, "avgDs18": 19.71, "samplxH": 37}]}