{"day": "2020-03-11", "latitude": 43.7744583, "longitude": 11.255065, "avgDailyTemp": 12.39, "avgDailyCo2": 429.1, "avgDailyRad": 72.0, "avgDailyO3": 124.84, "avgDailyNo2": 89.96, "avgDailyCo": 277.91, "avgDailyVoc": 358.91, "avgDailyPm2_5": 32.67, "avgDailyPm10": 12.46, "avgDailyDs18": 23.15, "data": [{"time": "2020-03-11_00", "missingData": "false", "avgTemp": 7.41, "avgCo2": 418.03, "avgRad": 85.27, "avg03": 139.7, "avgNo2": 72.68, "avgCo": 266.78, "avgVoc": 348.19, "avgPm2_5": 26.08, "avgPm10": 11.41, "avgDs18": 16.97, "samplxH": 37}, {"time": "2020-03-11_01", "missingData": "false", "avgTemp": 6.99, "avgCo2": 421.25, "avgRad": 87.4, "avg03": 150.5, "avgNo2": 73.22, "avgCo": 265.33, "avgVoc": 348.22, "avgPm2_5": 24.56, "avgPm10": 10.81, "avgDs18": 16.51, "samplxH": 36}, {"time": "2020-03-11_02", "missingData": "false", "avgTemp": 6.57, "avgCo2": 418.08, "avgRad": 89.65, "avg03": 148.97, "avgNo2": 74.55, "avgCo": 263.39, "avgVoc": 349.03, "avgPm2_5": 24.21, "avgPm10": 10.76, "avgDs18": 16.11, "samplxH": 38}, {"time": "2020-03-11_03", "missingData": "false", "avgTemp": 6.1, "avgCo2": 422.25, "avgRad": 91.58, "avg03": 121.11, "avgNo2": 81.14, "avgCo": 262.94, "avgVoc": 354.78, "avgPm2_5": 26.39, "avgPm10": 11.42, "avgDs18": 15.67, "samplxH": 36}, {"time": "2020-03-11_04", "missingData": "false", "avgTemp": 5.74, "avgCo2": 424.19, "avgRad": 92.93, "avg03": 107.68, "avgNo2": 84.86, "avgCo": 260.86, "avgVoc": 358.14, "avgPm2_5": 24.0, "avgPm10": 10.41, "avgDs18": 15.36, "samplxH": 37}, {"time": "2020-03-11_05", "missingData": "false", "avgTemp": 5.26, "avgCo2": 438.55, "avgRad": 94.18, "avg03": 47.47, "avgNo2": 103.13, "avgCo": 262.29, "avgVoc": 371.68, "avgPm2_5": 26.39, "avgPm10": 11.42, "avgDs18": 14.96, "samplxH": 38}, {"time": "2020-03-11_06", "missingData": "false", "avgTemp": 6.3, "avgCo2": 463.23, "avgRad": 91.26, "avg03": 33.63, "avgNo2": 89.09, "avgCo": 268.31, "avgVoc": 377.4, "avgPm2_5": 26.77, "avgPm10": 10.09, "avgDs18": 16.24, "samplxH": 35}, {"time": "2020-03-11_07", "missingData": "false", "avgTemp": 9.08, "avgCo2": 463.45, "avgRad": 81.22, "avg03": 26.7, "avgNo2": 110.85, "avgCo": 280.61, "avgVoc": 391.42, "avgPm2_5": 30.18, "avgPm10": 10.94, "avgDs18": 21.5, "samplxH": 33}, {"time": "2020-03-11_08", "missingData": "false", "avgTemp": 12.63, "avgCo2": 462.9, "avgRad": 71.25, "avg03": 23.16, "avgNo2": 126.1, "avgCo": 297.9, "avgVoc": 401.58, "avgPm2_5": 37.29, "avgPm10": 14.84, "avgDs18": 25.19, "samplxH": 31}, {"time": "2020-03-11_09", "missingData": "false", "avgTemp": 15.51, "avgCo2": 440.73, "avgRad": 62.41, "avg03": 27.84, "avgNo2": 125.27, "avgCo": 292.7, "avgVoc": 395.95, "avgPm2_5": 38.03, "avgPm10": 14.08, "avgDs18": 29.01, "samplxH": 37}, {"time": "2020-03-11_10", "missingData": "false", "avgTemp": 16.9, "avgCo2": 417.0, "avgRad": 54.31, "avg03": 96.79, "avgNo2": 89.93, "avgCo": 274.14, "avgVoc": 356.71, "avgPm2_5": 29.32, "avgPm10": 9.32, "avgDs18": 30.65, "samplxH": 28}, {"time": "2020-03-11_11", "missingData": "false", "avgTemp": 19.35, "avgCo2": 407.9, "avgRad": 46.4, "avg03": 145.23, "avgNo2": 85.81, "avgCo": 268.84, "avgVoc": 349.26, "avgPm2_5": 25.29, "avgPm10": 8.29, "avgDs18": 32.7, "samplxH": 31}, {"time": "2020-03-11_12", "missingData": "false", "avgTemp": 19.65, "avgCo2": 403.81, "avgRad": 44.47, "avg03": 196.38, "avgNo2": 76.12, "avgCo": 264.12, "avgVoc": 335.75, "avgPm2_5": 21.88, "avgPm10": 6.5, "avgDs18": 32.35, "samplxH": 32}, {"time": "2020-03-11_13", "missingData": "false", "avgTemp": 20.2, "avgCo2": 399.52, "avgRad": 43.67, "avg03": 240.86, "avgNo2": 72.69, "avgCo": 266.0, "avgVoc": 329.14, "avgPm2_5": 24.14, "avgPm10": 6.59, "avgDs18": 32.67, "samplxH": 29}, {"time": "2020-03-11_14", "missingData": "false", "avgTemp": 20.6, "avgCo2": 396.36, "avgRad": 45.41, "avg03": 249.88, "avgNo2": 72.85, "avgCo": 271.79, "avgVoc": 328.0, "avgPm2_5": 25.36, "avgPm10": 7.12, "avgDs18": 33.02, "samplxH": 33}, {"time": "2020-03-11_15", "missingData": "false", "avgTemp": 19.59, "avgCo2": 394.22, "avgRad": 48.71, "avg03": 250.0, "avgNo2": 66.91, "avgCo": 274.41, "avgVoc": 322.62, "avgPm2_5": 26.94, "avgPm10": 7.31, "avgDs18": 31.36, "samplxH": 32}, {"time": "2020-03-11_16", "missingData": "false", "avgTemp": 18.44, "avgCo2": 406.94, "avgRad": 55.69, "avg03": 250.0, "avgNo2": 66.29, "avgCo": 285.03, "avgVoc": 325.45, "avgPm2_5": 30.32, "avgPm10": 9.26, "avgDs18": 29.69, "samplxH": 31}, {"time": "2020-03-11_17", "missingData": "false", "avgTemp": 16.91, "avgCo2": 417.94, "avgRad": 59.52, "avg03": 249.86, "avgNo2": 67.49, "avgCo": 290.63, "avgVoc": 332.43, "avgPm2_5": 37.69, "avgPm10": 13.17, "avgDs18": 26.53, "samplxH": 35}, {"time": "2020-03-11_18", "missingData": "false", "avgTemp": 15.27, "avgCo2": 416.67, "avgRad": 62.15, "avg03": 223.13, "avgNo2": 71.43, "avgCo": 285.53, "avgVoc": 338.4, "avgPm2_5": 47.4, "avgPm10": 18.37, "avgDs18": 24.39, "samplxH": 30}, {"time": "2020-03-11_19", "missingData": "false", "avgTemp": 13.78, "avgCo2": 426.3, "avgRad": 66.35, "avg03": 176.38, "avgNo2": 82.59, "avgCo": 288.65, "avgVoc": 351.62, "avgPm2_5": 40.59, "avgPm10": 14.73, "avgDs18": 23.04, "samplxH": 37}, {"time": "2020-03-11_20", "missingData": "false", "avgTemp": 12.35, "avgCo2": 479.58, "avgRad": 77.09, "avg03": 26.58, "avgNo2": 139.26, "avgCo": 315.68, "avgVoc": 398.9, "avgPm2_5": 56.19, "avgPm10": 24.13, "avgDs18": 21.8, "samplxH": 31}, {"time": "2020-03-11_21", "missingData": "false", "avgTemp": 10.84, "avgCo2": 463.0, "avgRad": 82.53, "avg03": 22.89, "avgNo2": 121.14, "avgCo": 301.08, "avgVoc": 389.78, "avgPm2_5": 52.31, "avgPm10": 22.33, "avgDs18": 20.49, "samplxH": 36}, {"time": "2020-03-11_22", "missingData": "false", "avgTemp": 9.98, "avgCo2": 446.06, "avgRad": 84.91, "avg03": 34.03, "avgNo2": 103.58, "avgCo": 288.9, "avgVoc": 378.06, "avgPm2_5": 44.48, "avgPm10": 18.65, "avgDs18": 19.44, "samplxH": 31}, {"time": "2020-03-11_23", "missingData": "false", "avgTemp": 9.23, "avgCo2": 443.18, "avgRad": 86.4, "avg03": 44.79, "avgNo2": 101.62, "avgCo": 281.03, "avgVoc": 373.21, "avgPm2_5": 41.15, "avgPm10": 16.44, "avgDs18": 18.72, "samplxH": 34}]}