{"day": "2020-06-08", "latitude": 43.7881434, "longitude": 11.2266357, "avgDailyTemp": 22.07, "avgDailyCo2": 427.28, "avgDailyRad": 64.51, "avgDailyO3": 23.29, "avgDailyNo2": 199.11, "avgDailyCo": 246.19, "avgDailyVoc": 870.54, "avgDailyPm2_5": 7.54, "avgDailyPm10": 258.75, "avgDailyDs18": 32.06, "data": [{"time": "2020-06-08_00", "missingData": "false", "avgTemp": 21.19, "avgCo2": 457.49, "avgRad": 80.92, "avg03": 20.05, "avgNo2": 239.38, "avgCo": 259.0, "avgVoc": 911.24, "avgPm2_5": 8.11, "avgPm10": 0.89, "avgDs18": 31.54, "samplxH": 37}, {"time": "2020-06-08_01", "missingData": "false", "avgTemp": 21.02, "avgCo2": 452.92, "avgRad": 79.38, "avg03": 20.41, "avgNo2": 234.92, "avgCo": 253.59, "avgVoc": 900.0, "avgPm2_5": 7.65, "avgPm10": 0.78, "avgDs18": 31.48, "samplxH": 37}, {"time": "2020-06-08_02", "missingData": "false", "avgTemp": 20.89, "avgCo2": 447.0, "avgRad": 77.37, "avg03": 20.86, "avgNo2": 230.35, "avgCo": 250.0, "avgVoc": 892.11, "avgPm2_5": 7.59, "avgPm10": 0.73, "avgDs18": 31.31, "samplxH": 37}, {"time": "2020-06-08_03", "missingData": "false", "avgTemp": 20.44, "avgCo2": 442.53, "avgRad": 77.02, "avg03": 21.0, "avgNo2": 220.18, "avgCo": 247.21, "avgVoc": 879.11, "avgPm2_5": 7.45, "avgPm10": 0.68, "avgDs18": 30.97, "samplxH": 38}, {"time": "2020-06-08_04", "missingData": "false", "avgTemp": 20.35, "avgCo2": 441.67, "avgRad": 75.71, "avg03": 21.0, "avgNo2": 217.9, "avgCo": 246.23, "avgVoc": 887.41, "avgPm2_5": 7.64, "avgPm10": 0.87, "avgDs18": 30.88, "samplxH": 39}, {"time": "2020-06-08_05", "missingData": "false", "avgTemp": 20.51, "avgCo2": 441.55, "avgRad": 75.0, "avg03": 21.34, "avgNo2": 212.68, "avgCo": 252.79, "avgVoc": 903.71, "avgPm2_5": 7.61, "avgPm10": 0.87, "avgDs18": 30.98, "samplxH": 38}, {"time": "2020-06-08_06", "missingData": "false", "avgTemp": 21.1, "avgCo2": 433.71, "avgRad": 72.23, "avg03": 22.0, "avgNo2": 207.18, "avgCo": 258.82, "avgVoc": 907.82, "avgPm2_5": 7.79, "avgPm10": 0.88, "avgDs18": 31.39, "samplxH": 34}, {"time": "2020-06-08_07", "missingData": "false", "avgTemp": 21.76, "avgCo2": 425.59, "avgRad": 69.49, "avg03": 21.73, "avgNo2": 207.0, "avgCo": 275.65, "avgVoc": 914.86, "avgPm2_5": 7.89, "avgPm10": 0.86, "avgDs18": 31.88, "samplxH": 37}, {"time": "2020-06-08_08", "missingData": "false", "avgTemp": 22.29, "avgCo2": 431.86, "avgRad": 67.66, "avg03": 21.0, "avgNo2": 214.26, "avgCo": 294.23, "avgVoc": 923.77, "avgPm2_5": 7.86, "avgPm10": 0.77, "avgDs18": 32.34, "samplxH": 35}, {"time": "2020-06-08_09", "missingData": "false", "avgTemp": 23.1, "avgCo2": 426.09, "avgRad": 65.33, "avg03": 21.6, "avgNo2": 214.03, "avgCo": 272.97, "avgVoc": 913.2, "avgPm2_5": 8.29, "avgPm10": 0.74, "avgDs18": 32.99, "samplxH": 35}, {"time": "2020-06-08_10", "missingData": "false", "avgTemp": 23.49, "avgCo2": 418.46, "avgRad": 64.5, "avg03": 22.17, "avgNo2": 210.51, "avgCo": 255.43, "avgVoc": 890.17, "avgPm2_5": 8.09, "avgPm10": 0.83, "avgDs18": 33.18, "samplxH": 35}, {"time": "2020-06-08_11", "missingData": "false", "avgTemp": 23.13, "avgCo2": 415.92, "avgRad": 64.59, "avg03": 22.87, "avgNo2": 205.39, "avgCo": 253.13, "avgVoc": 877.74, "avgPm2_5": 7.84, "avgPm10": 216.08, "avgDs18": 33.16, "samplxH": 38}, {"time": "2020-06-08_12", "missingData": "false", "avgTemp": 21.72, "avgCo2": 417.86, "avgRad": 72.52, "avg03": 23.44, "avgNo2": 190.14, "avgCo": 251.94, "avgVoc": 844.92, "avgPm2_5": 7.56, "avgPm10": 227.94, "avgDs18": 31.87, "samplxH": 36}, {"time": "2020-06-08_13", "missingData": "false", "avgTemp": 23.96, "avgCo2": 417.62, "avgRad": 62.59, "avg03": 23.0, "avgNo2": 202.12, "avgCo": 263.29, "avgVoc": 879.12, "avgPm2_5": 7.53, "avgPm10": 241.15, "avgDs18": 33.44, "samplxH": 34}, {"time": "2020-06-08_14", "missingData": "false", "avgTemp": 25.32, "avgCo2": 412.41, "avgRad": 54.89, "avg03": 23.0, "avgNo2": 207.15, "avgCo": 259.03, "avgVoc": 900.06, "avgPm2_5": 7.09, "avgPm10": 120.44, "avgDs18": 34.88, "samplxH": 34}, {"time": "2020-06-08_15", "missingData": "false", "avgTemp": 25.13, "avgCo2": 406.97, "avgRad": 47.49, "avg03": 23.84, "avgNo2": 190.29, "avgCo": 241.32, "avgVoc": 868.97, "avgPm2_5": 6.97, "avgPm10": 646.66, "avgDs18": 34.46, "samplxH": 38}, {"time": "2020-06-08_16", "missingData": "false", "avgTemp": 24.93, "avgCo2": 409.85, "avgRad": 40.07, "avg03": 25.0, "avgNo2": 177.79, "avgCo": 226.53, "avgVoc": 869.85, "avgPm2_5": 7.09, "avgPm10": 843.15, "avgDs18": 34.2, "samplxH": 34}, {"time": "2020-06-08_17", "missingData": "false", "avgTemp": 23.77, "avgCo2": 413.94, "avgRad": 40.43, "avg03": 25.74, "avgNo2": 165.09, "avgCo": 217.37, "avgVoc": 845.34, "avgPm2_5": 6.8, "avgPm10": 702.0, "avgDs18": 33.22, "samplxH": 35}, {"time": "2020-06-08_18", "missingData": "false", "avgTemp": 22.87, "avgCo2": 419.65, "avgRad": 43.65, "avg03": 26.27, "avgNo2": 160.73, "avgCo": 216.41, "avgVoc": 833.19, "avgPm2_5": 7.0, "avgPm10": 1106.76, "avgDs18": 32.45, "samplxH": 37}, {"time": "2020-06-08_19", "missingData": "false", "avgTemp": 21.9, "avgCo2": 423.76, "avgRad": 50.98, "avg03": 26.91, "avgNo2": 159.48, "avgCo": 220.42, "avgVoc": 821.91, "avgPm2_5": 6.97, "avgPm10": 372.27, "avgDs18": 31.67, "samplxH": 33}, {"time": "2020-06-08_20", "missingData": "false", "avgTemp": 21.34, "avgCo2": 425.86, "avgRad": 57.82, "avg03": 24.56, "avgNo2": 208.19, "avgCo": 214.39, "avgVoc": 824.92, "avgPm2_5": 7.25, "avgPm10": 910.08, "avgDs18": 30.9, "samplxH": 36}, {"time": "2020-06-08_21", "missingData": "false", "avgTemp": 20.49, "avgCo2": 422.85, "avgRad": 64.4, "avg03": 27.44, "avgNo2": 164.67, "avgCo": 221.59, "avgVoc": 798.87, "avgPm2_5": 7.51, "avgPm10": 525.03, "avgDs18": 30.46, "samplxH": 39}, {"time": "2020-06-08_22", "missingData": "false", "avgTemp": 20.03, "avgCo2": 422.79, "avgRad": 69.43, "avg03": 27.53, "avgNo2": 165.45, "avgCo": 229.11, "avgVoc": 802.76, "avgPm2_5": 7.82, "avgPm10": 0.29, "avgDs18": 30.25, "samplxH": 38}, {"time": "2020-06-08_23", "missingData": "false", "avgTemp": 20.02, "avgCo2": 421.68, "avgRad": 69.06, "avg03": 26.29, "avgNo2": 171.29, "avgCo": 231.45, "avgVoc": 810.82, "avgPm2_5": 7.45, "avgPm10": 323.53, "avgDs18": 30.4, "samplxH": 38}]}